ahio/__init__.py
ahio/abstract_driver.py
ahio/drivers/__init__.py
ahio/drivers/arduino.py
ahio/drivers/dummy.py
ahio/drivers/generic_tcp_io.py
ahio/drivers/modbus.py
ahio/drivers/raspberry.py
ahio/drivers/siso_model.py
ahio/drivers/snap7.py
ahio-1.0.35.dist-info/METADATA
ahio-1.0.35.dist-info/WHEEL
ahio-1.0.35.dist-info/licenses/LICENSE.txt
ahio-1.0.35.dist-info/RECORD
