Metadata-Version: 2.4
Name: ahio
Version: 1.0.35
Summary: I/O Communication Library
Project-URL: Repository, https://github.com/acristoffers/ahio
Author-email: Álan Crístoffer <acristoffers@startmail.com>
License-Expression: MIT
License-File: LICENSE.txt
Keywords: I/O,data acquisition,hardware communication
Requires-Python: <3.15,>=3.8
Requires-Dist: pymodbus<4,>=3.0.0
Requires-Dist: pyserial~=3.5
Requires-Dist: python-snap7~=1.3
